[
    {
        "_from": "iso_639",
        "_to": "iso",
        "_rels_predicate": "_enum_pred_section-of",
        "_rels_path": ["iso"]
    },
    {
        "_from": "iso_3166",
        "_to": "iso",
        "_rels_predicate": "_enum_pred_section-of",
        "_rels_path": ["iso"]
    },
    {
        "_from": "iso_4217",
        "_to": "iso",
        "_rels_predicate": "_enum_pred_section-of",
        "_rels_path": ["iso"]
    },
    {
        "_from": "iso_15924",
        "_to": "iso",
        "_rels_predicate": "_enum_pred_section-of",
        "_rels_path": ["iso"]
    },
    
    {
        "_from": "iso_639_1",
        "_to": "iso_639",
        "_rels_predicate": "_enum_pred_section-of",
        "_rels_path": ["iso"]
    },
    {
        "_from": "iso_639_2",
        "_to": "iso_639",
        "_rels_predicate": "_enum_pred_section-of",
        "_rels_path": ["iso"]
    },
    {
        "_from": "iso_639_3",
        "_to": "iso_639",
        "_rels_predicate": "_enum_pred_section-of",
        "_rels_path": ["iso"]
    },
    {
        "_from": "iso_639_5",
        "_to": "iso_639",
        "_rels_predicate": "_enum_pred_section-of",
        "_rels_path": ["iso"]
    },    
    {
        "_from": "iso_639_scopes",
        "_to": "iso_639",
        "_rels_predicate": "_enum_pred_section-of",
        "_rels_path": ["iso"]
    },
    {
        "_from": "iso_639_types",
        "_to": "iso_639",
        "_rels_predicate": "_enum_pred_section-of",
        "_rels_path": ["iso"]
    },

    {
        "_from": "iso_639_scopes_I",
        "_to": "iso_639_3",
        "_rels_predicate": "_enum_pred_section-of",
        "_rels_path": ["iso_639_3"]
    },
    {
        "_from": "iso_639_scopes_M",
        "_to": "iso_639_3",
        "_rels_predicate": "_enum_pred_section-of",
        "_rels_path": ["iso_639_3"]
    },
    {
        "_from": "iso_639_scopes_S",
        "_to": "iso_639_3",
        "_rels_predicate": "_enum_pred_section-of",
        "_rels_path": ["iso_639_3"]
    },

    {
        "_from": "iso_639_types_A",
        "_to": "iso_639_scopes_I",
        "_rels_predicate": "_enum_pred_section-of",
        "_rels_path": ["iso_639_3"]
    },
    {
        "_from": "iso_639_types_C",
        "_to": "iso_639_scopes_I",
        "_rels_predicate": "_enum_pred_section-of",
        "_rels_path": ["iso_639_3"]
    },
    {
        "_from": "iso_639_types_E",
        "_to": "iso_639_scopes_I",
        "_rels_predicate": "_enum_pred_section-of",
        "_rels_path": ["iso_639_3"]
    },
    {
        "_from": "iso_639_types_H",
        "_to": "iso_639_scopes_I",
        "_rels_predicate": "_enum_pred_section-of",
        "_rels_path": ["iso_639_3"]
    },
    {
        "_from": "iso_639_types_L",
        "_to": "iso_639_scopes_I",
        "_rels_predicate": "_enum_pred_section-of",
        "_rels_path": ["iso_639_3"]
    },
    
    {
        "_from": "iso_3166_1",
        "_to": "iso_3166",
        "_rels_predicate": "_enum_pred_section-of",
        "_rels_path": ["iso"]
    },
    {
        "_from": "iso_3166_2",
        "_to": "iso_3166",
        "_rels_predicate": "_enum_pred_section-of",
        "_rels_path": ["iso"]
    },
    {
        "_from": "iso_3166_3",
        "_to": "iso_3166",
        "_rels_predicate": "_enum_pred_section-of",
        "_rels_path": ["iso"]
    },
    
    {
        "_from": "iso_639_scopes_I",
        "_to": "iso_639_scopes",
        "_rels_predicate": "_enum_pred_enum-of",
        "_rels_path": ["iso"]
    },
    {
        "_from": "iso_639_scopes_M",
        "_to": "iso_639_scopes",
        "_rels_predicate": "_enum_pred_enum-of",
        "_rels_path": ["iso"]
    },
    {
        "_from": "iso_639_scopes_S",
        "_to": "iso_639_scopes",
        "_rels_predicate": "_enum_pred_enum-of",
        "_rels_path": ["iso"]
    },
    
    {
        "_from": "iso_639_types_A",
        "_to": "iso_639_types",
        "_rels_predicate": "_enum_pred_enum-of",
        "_rels_path": ["iso"]
    },
    {
        "_from": "iso_639_types_C",
        "_to": "iso_639_types",
        "_rels_predicate": "_enum_pred_enum-of",
        "_rels_path": ["iso"]
    },
    {
        "_from": "iso_639_types_E",
        "_to": "iso_639_types",
        "_rels_predicate": "_enum_pred_enum-of",
        "_rels_path": ["iso"]
    },
    {
        "_from": "iso_639_types_H",
        "_to": "iso_639_types",
        "_rels_predicate": "_enum_pred_enum-of",
        "_rels_path": ["iso"]
    },
    {
        "_from": "iso_639_types_L",
        "_to": "iso_639_types",
        "_rels_predicate": "_enum_pred_enum-of",
        "_rels_path": ["iso"]
    },
    {
        "_from": "iso_639_types_S",
        "_to": "iso_639_types",
        "_rels_predicate": "_enum_pred_enum-of",
        "_rels_path": ["iso"]
    }


]